MANIFEST.in
README.txt
setup.cfg
setup.py
Products/__init__.py
Products.humanator.egg-info/PKG-INFO
Products.humanator.egg-info/SOURCES.txt
Products.humanator.egg-info/dependency_links.txt
Products.humanator.egg-info/entry_points.txt
Products.humanator.egg-info/namespace_packages.txt
Products.humanator.egg-info/not-zip-safe
Products.humanator.egg-info/requires.txt
Products.humanator.egg-info/top_level.txt
Products/humanator/__init__.py
Products/humanator/config.py
Products/humanator/configure.zcml
Products/humanator/interfaces.py
Products/humanator/tests.py
Products/humanator/version.txt
Products/humanator/browser/__init__.py
Products/humanator/browser/configure.zcml
Products/humanator/browser/humanator.py
Products/humanator/browser/humanatorfolder.py
Products/humanator/browser/humanatorfolder_view.pt
Products/humanator/browser/humanatorquestion.py
Products/humanator/browser/humanatorquestion_view.pt
Products/humanator/browser/interfaces.py
Products/humanator/content/__init__.py
Products/humanator/content/configure.zcml
Products/humanator/content/humanatorfolder.py
Products/humanator/content/humanatorquestion.py
Products/humanator/form/__init__.py
Products/humanator/form/configure.zcml
Products/humanator/form/field.py
Products/humanator/form/interfaces.py
Products/humanator/form/widget.py
Products/humanator/profiles/default/Products.humanator_various.txt
Products/humanator/profiles/default/factorytool.xml
Products/humanator/profiles/default/rolemap.xml
Products/humanator/profiles/default/types.xml
Products/humanator/profiles/default/types/Humanator_folder.xml
Products/humanator/profiles/default/types/Humanator_question.xml
docs/HISTORY.txt
docs/INSTALL.txt
docs/LICENSE.GPL
docs/LICENSE.txt
